CTkListbox/__init__.py
CTkListbox/ctk_listbox.py
CTkListbox-1.4.dist-info/LICENSE
CTkListbox-1.4.dist-info/METADATA
CTkListbox-1.4.dist-info/WHEEL
CTkListbox-1.4.dist-info/dependency_links.txt
CTkListbox-1.4.dist-info/top_level.txt
CTkListbox-1.4.dist-info/RECORD
