Metadata-Version: 2.1
Name: CTkListbox
Version: 1.4
Summary: Customtkinter Listbox widget
Home-page: https://github.com/Akascape/CTkListbox
Author: Akash Bora
License: MIT
Keywords: customtkinter,tkinter,listbox-widget,listbox,modern-listbox,option menu,list-box,ctklistbox
Classifier: License :: OSI Approved :: MIT License 
Classifier: Programming Language :: Python :: 3
Classifier: Operating System :: OS Independent
Requires-Python: >=3.6
License-File: LICENSE
Requires-Dist: customtkinter
